asff/__init__.py
asff/constants.py
asff/exceptions.py
asff/finding.py
asff/generated.py
asff-0.1.1.dist-info/LICENSE
asff-0.1.1.dist-info/WHEEL
asff-0.1.1.dist-info/METADATA
asff-0.1.1.dist-info/RECORD
