Metadata-Version: 2.1
Name: asff
Version: 0.1.1
Summary: asff is a Python library to work with Amazon Security Finding Format
Home-page: https://github.com/xen0l/python-asff
License: BSD-3-Clause
Keywords: security,aws,asff,secuityhub
Author: Adam Števko
Author-email: adam.stevko@gmail.com
Maintainer: Adam Števko
Maintainer-email: adam.stevko@gmail.com
Requires-Python: >=3.6.1,<4.0.0
Classifier: License :: OSI Approved :: BSD License
Classifier: Programming Language :: Python :: 3
Classifier: Programming Language :: Python :: 3.7
Classifier: Programming Language :: Python :: 3.8
Classifier: Programming Language :: Python :: 3.9
Classifier: Topic :: Security
Requires-Dist: pydantic (>=1.7.2,<2.0.0)
Project-URL: Bug Tracker, https://github.com/xen0l/python-asff/issues
Project-URL: Documentation, https://python-asff.readthedocs.io/
Project-URL: Repository, https://github.com/xen0l/python-asff
